je_load_density/__init__.py
je_load_density/__main__.py
je_load_density/gui/__init__.py
je_load_density/gui/load_density_gui_thread.py
je_load_density/gui/log_to_ui_filter.py
je_load_density/gui/main_widget.py
je_load_density/gui/main_window.py
je_load_density/gui/language_wrapper/__init__.py
je_load_density/gui/language_wrapper/english.py
je_load_density/gui/language_wrapper/multi_language_wrapper.py
je_load_density/gui/language_wrapper/traditional_chinese.py
je_load_density/utils/__init__.py
je_load_density/utils/callback/__init__.py
je_load_density/utils/callback/callback_function_executor.py
je_load_density/utils/exception/__init__.py
je_load_density/utils/exception/exception_tags.py
je_load_density/utils/exception/exceptions.py
je_load_density/utils/executor/__init__.py
je_load_density/utils/executor/action_executor.py
je_load_density/utils/file_process/__init__.py
je_load_density/utils/file_process/create_project_structure.py
je_load_density/utils/file_process/get_dir_file_list.py
je_load_density/utils/generate_report/__init__.py
je_load_density/utils/generate_report/generate_html_report.py
je_load_density/utils/generate_report/generate_json_report.py
je_load_density/utils/generate_report/generate_xml_report.py
je_load_density/utils/get_data_strcture/__init__.py
je_load_density/utils/get_data_strcture/get_api_data.py
je_load_density/utils/json/__init__.py
je_load_density/utils/json/json_file/__init__.py
je_load_density/utils/json/json_file/json_file.py
je_load_density/utils/json/json_format/__init__.py
je_load_density/utils/json/json_format/json_process.py
je_load_density/utils/logging/__init__.py
je_load_density/utils/logging/loggin_instance.py
je_load_density/utils/package_manager/__init__.py
je_load_density/utils/package_manager/package_manager_class.py
je_load_density/utils/project/__init__.py
je_load_density/utils/project/create_project_structure.py
je_load_density/utils/project/template/__init__.py
je_load_density-0.0.64.dist-info/licenses/LICENSE
je_load_density-0.0.64.dist-info/METADATA
je_load_density-0.0.64.dist-info/WHEEL
je_load_density-0.0.64.dist-info/top_level.txt
je_load_density-0.0.64.dist-info/RECORD
