Metadata-Version: 2.4
Name: je_load_density
Version: 0.0.64
Summary: Load & Stress Automation Freamework
Author-email: JE-Chen <jechenmailman@gmail.com>
Project-URL: Homepage, https://github.com/Intergration-Automation-Testing/LoadDensity
Project-URL: Documentation, https://loaddensity.readthedocs.io/en/latest/
Project-URL: Code, https://github.com/Intergration-Automation-Testing/LoadDensity
Classifier: Programming Language :: Python :: 3.10
Classifier: Development Status :: 2 - Pre-Alpha
Classifier: Environment :: Win32 (MS Windows)
Classifier: Environment :: MacOS X
Classifier: Environment :: X11 Applications
Classifier: Operating System :: OS Independent
Requires-Python: >=3.10
License-File: LICENSE
Requires-Dist: locust
Provides-Extra: gui
Requires-Dist: PySide6==6.10.0; extra == "gui"
Requires-Dist: qt-material; extra == "gui"
Dynamic: license-file
